icon_lib/__init__.py
icon_lib/voyager_icon.py
voyager_icon-0.0.1.dist-info/LICENSE
voyager_icon-0.0.1.dist-info/METADATA
voyager_icon-0.0.1.dist-info/WHEEL
voyager_icon-0.0.1.dist-info/top_level.txt
voyager_icon-0.0.1.dist-info/RECORD
